{"cameraMode":{"drawMode":0,"name":"Shaded","section":"Shading Mode"},"sceneLighting":true,"audioPlay":false,"sceneViewState":{"showFog":true,"showMaterialUpdate":false,"showSkybox":true,"showFlares":true,"showImageEffects":true,"showParticleSystems":true},"in2DMode":false,"pivot":{"x":7.473114967346191,"y":6.292359828948975,"z":-42.643585205078128},"rotation":{"x":-0.0010369751835241914,"y":-0.9879772663116455,"z":0.00470757158473134,"w":-0.15533402562141419},"size":13.642505645751954,"orthographic":false}